tcpping_mcp_server-0.1.5.dist-info/licenses/LICENSE
tcpping_mcp_stdio/__init__.py
tcpping_mcp_stdio/mcp.json
tcpping_mcp_stdio/modern_server.py
tcpping_mcp_stdio/tcpping_core.py
tcpping_mcp_server-0.1.5.dist-info/METADATA
tcpping_mcp_server-0.1.5.dist-info/WHEEL
tcpping_mcp_server-0.1.5.dist-info/entry_points.txt
tcpping_mcp_server-0.1.5.dist-info/top_level.txt
tcpping_mcp_server-0.1.5.dist-info/RECORD
