Metadata-Version: 2.4
Name: tcpping-mcp-server
Version: 0.1.5
Summary: A modern MCP server for TCP ping testing via pingloc.com
Author-email: chenxizhang <ares@xizhang.com>
License-Expression: MIT
Project-URL: Homepage, https://github.com/chenxizhang/devbox
Project-URL: Repository, https://github.com/chenxizhang/devbox
Project-URL: Issues, https://github.com/chenxizhang/devbox/issues
Project-URL: Source (Subdir), https://github.com/chenxizhang/devbox/tree/master/tcpping/mcp/stdio
Keywords: tcp,ping,latency,mcp,model context protocol,playwright
Classifier: Development Status :: 3 - Alpha
Classifier: Intended Audience :: Developers
Classifier: Topic :: Internet :: WWW/HTTP
Classifier: Topic :: System :: Monitoring
Classifier: Programming Language :: Python
Classifier: Programming Language :: Python :: 3
Classifier: Programming Language :: Python :: 3.9
Classifier: Programming Language :: Python :: 3.10
Classifier: Programming Language :: Python :: 3.11
Classifier: Programming Language :: Python :: 3.12
Requires-Python: >=3.9
License-File: LICENSE
Requires-Dist: playwright>=1.45.0
Requires-Dist: fastmcp>=0.1.0
Dynamic: license-file
